nats_consumer/__init__.py
nats_consumer/apps.py
nats_consumer/client.py
nats_consumer/consumer.py
nats_consumer/exceptions.py
nats_consumer/handler.py
nats_consumer/migrations.py
nats_consumer/operations.py
nats_consumer/settings.py
nats_consumer/management/commands/__init__.py
nats_consumer/management/commands/nats_consumer.py
nats_consumer/management/commands/nats_delete_stream.py
nats_consumer/management/commands/nats_update_stream.py
oxnats-2.0.0.dist-info/METADATA
oxnats-2.0.0.dist-info/WHEEL
oxnats-2.0.0.dist-info/licenses/LICENSE
oxnats-2.0.0.dist-info/RECORD
