Metadata-Version: 2.4
Name: oxnats
Version: 2.0.0
Summary: Django NATS Consumer
Project-URL: Homepage, https://github.com/dev360/django-nats-consumer
Project-URL: Repository, https://github.com/dev360/django-nats-consumer
License-Expression: BSD-3-Clause
License-File: LICENSE
Keywords: async,consumer,django,jetstream,nats
Classifier: Development Status :: 4 - Beta
Classifier: Environment :: Web Environment
Classifier: Framework :: Django
Classifier: Intended Audience :: Developers
Classifier: Operating System :: OS Independent
Classifier: Programming Language :: Python
Classifier: Programming Language :: Python :: 3.8
Classifier: Programming Language :: Python :: 3.9
Classifier: Programming Language :: Python :: 3.10
Classifier: Programming Language :: Python :: 3.11
Classifier: Programming Language :: Python :: 3.12
Classifier: Programming Language :: Python :: 3.13
Requires-Python: >=3.9
Requires-Dist: django>=4.1
Requires-Dist: nats-py>=2.9.0
Provides-Extra: dev
Requires-Dist: watchfiles>=1.0.4; (python_version < '3.14') and extra == 'dev'
Provides-Extra: uvloop
Requires-Dist: uvloop>=0.21.0; extra == 'uvloop'
